{
  "bow-title": "Mi\u0161ko Rov\u010danin Tiron",
  "bow-link": "http://mrbows.com/en/serbian-bow-tiron/",
  "samples": [
    {
      "bow-title": "MR Tiron 60\" - 92#@28\"",
      "contributed-by": { "facebook": "R Sauqi" },
      "unstrung-length": "Not Measured",
      "strung-length": "Not Measured",
      "min-box-dim": {
        "length": "Not Measured",
        "width": "Not Measured",
        "depth": "Not Measured"
      },
      "siyahs": {
        "effective-top-length": "Not Measured",
        "effective-bottom-length": "Not Measured",
        "effective-top-angle": "Not Measured",
        "effective-bottom-angle": "Not Measured"
      },
      "bow-mass": "Not Measured",
      "grip-dim": {
        "length": "Not Measured",
        "width": "Not Measured",
        "thickness": "Not Measured"
      },
      "max-limb-thickness": "Not Measured",
      "min-limb-thickness": "Not Measured",
      "max-limb-width": "Not Measured",
      "min-limb-width": "Not Measured",
      "arrow-pass-width": "Not Measured",
      "max-draw": 34,
      "stock-string-length": { "max": "Not Measured", "min": "Not Measured" },
      "brace-height": 20,
      "manufacture-date": "",
      "measurement-date": "",
      "comments": "Measured by R Sauqi",
      "asym": false,
      "asym-length": { "top": "Not Measured", "bottom": "Not Measured" },
      "df-data": [
        { "x": 9, "y": 12.7 },
        { "x": 10, "y": 20.8 },
        { "x": 11, "y": 27 },
        { "x": 12, "y": 32.8 },
        { "x": 13, "y": 37.6 },
        { "x": 14, "y": 42.7 },
        { "x": 15, "y": 47.5 },
        { "x": 16, "y": 51.5 },
        { "x": 17, "y": 55 },
        { "x": 18, "y": 58.5 },
        { "x": 19, "y": 62.4 },
        { "x": 20, "y": 65.6 },
        { "x": 21, "y": 69 },
        { "x": 22, "y": 72.6 },
        { "x": 23, "y": 75.6 },
        { "x": 24, "y": 79.4 },
        { "x": 25, "y": 84 },
        { "x": 26, "y": 87.6 },
        { "x": 27, "y": 91.9 },
        { "x": 28, "y": 96.3 },
        { "x": 29, "y": 102.2 },
        { "x": 30, "y": 107 },
        { "x": 31, "y": 113.6 },
        { "x": 32, "y": 120.2 },
        { "x": 33, "y": 127.3 },
        { "x": 34, "y": 135.2 }
      ],
      "central-differences": [
        { "x": 9.0, "y": 10.074999999999998 },
        { "x": 10.0, "y": 5.725000000000016 },
        { "x": 11.0, "y": 5.924999999999997 },
        { "x": 12.0, "y": 5.241666666666667 },
        { "x": 13.0, "y": 4.891666666666672 },
        { "x": 14.0, "y": 5.041666666666666 },
        { "x": 15.0, "y": 4.41666666666666 },
        { "x": 16.0, "y": 3.6833333333333336 },
        { "x": 17.0, "y": 3.4250000000000043 },
        { "x": 18.0, "y": 3.7583333333333284 },
        { "x": 19.0, "y": 3.566666666666663 },
        { "x": 20.0, "y": 3.2250000000000068 },
        { "x": 21.0, "y": 3.566666666666661 },
        { "x": 22.0, "y": 3.249999999999993 },
        { "x": 23.0, "y": 3.2833333333333456 },
        { "x": 24.0, "y": 4.350000000000007 },
        { "x": 25.0, "y": 4.108333333333318 },
        { "x": 26.0, "y": 3.8583333333333343 },
        { "x": 27.0, "y": 4.283333333333331 },
        { "x": 28.0, "y": 5.249999999999991 },
        { "x": 29.0, "y": 5.325000000000006 },
        { "x": 30.0, "y": 5.608333333333327 },
        { "x": 31.0, "y": 6.70833333333333 },
        { "x": 32.0, "y": 6.783333333333346 },
        { "x": 33.0, "y": 8.091666666666583 },
        { "x": 34.0, "y": 8.349999999999909 }
      ],
      "regression-estimation": {
        "df-curve": [
          { "x": "9", "y": 12.510770026977362 },
          { "x": "10", "y": 20.43811493195549 },
          { "x": "11", "y": 27.288067593214798 },
          { "x": "12", "y": 33.259114132910135 },
          { "x": "13", "y": 38.51928691770209 },
          { "x": "14", "y": 43.211366622746034 },
          { "x": "15", "y": 47.45725076632363 },
          { "x": "16", "y": 51.361627417758555 },
          { "x": "17", "y": 55.015070213096706 },
          { "x": "18", "y": 58.49665196606555 },
          { "x": "19", "y": 61.876158427299416 },
          { "x": "20", "y": 65.2159706140272 },
          { "x": "21", "y": 68.5726731803195 },
          { "x": "22", "y": 71.99843716948365 },
          { "x": "23", "y": 75.54221788867052 },
          { "x": "24", "y": 79.25080232352684 },
          { "x": "25", "y": 83.16973526101415 },
          { "x": "26", "y": 87.34414893878 },
          { "x": "27", "y": 91.81951744580064 },
          { "x": "28", "y": 96.64235414149809 },
          { "x": "29", "y": 101.86086793931273 },
          { "x": "30", "y": 107.52559233276656 },
          { "x": "31", "y": 113.6899994584544 },
          { "x": "32", "y": 120.41111023407487 },
          { "x": "33", "y": 127.75011063341788 },
          { "x": "34", "y": 135.77298342540237 }
        ],
        "coeffs": [
          -0.17921284619161987, 0.09282258512113707, 38.76332083968939,
          0.35358198547498326, 46.837027882972
        ],
        "regression-eqn": "-216.29766874101458e^-0.17921284619161987x + -1.9729723230717655e^0.09282258512113707x46.837027882972",
        "regression-derivative": "38.76332083968939e^-0.17921284619161987x + 0.35358198547498326e^0.09282258512113707x",
        "regression-derivative-values": [
          { "x": "9", "y": 8.541018961518061 },
          { "x": "10", "y": 7.352738297342569 },
          { "x": "11", "y": 6.3801451593649805 },
          { "x": "12", "y": 5.589867005875759 },
          { "x": "13", "y": 4.954202862479127 },
          { "x": "14", "y": 4.45021184723302 },
          { "x": "15", "y": 4.058953098290477 },
          { "x": "16", "y": 3.764852443550917 },
          { "x": "17", "y": 3.5551752154766434 },
          { "x": "18", "y": 3.419588012852748 },
          { "x": "19", "y": 3.3497950541455963 },
          { "x": "20", "y": 3.339237145610586 },
          { "x": "21", "y": 3.3828432778058684 },
          { "x": "22", "y": 3.476826530562849 },
          { "x": "23", "y": 3.6185173621647992 },
          { "x": "24", "y": 3.8062285281692843 },
          { "x": "25", "y": 4.039146856350965 },
          { "x": "26", "y": 4.31724792790782 },
          { "x": "27", "y": 4.6412304075355335 },
          { "x": "28", "y": 5.012467348141675 },
          { "x": "29", "y": 5.432972288195432 },
          { "x": "30", "y": 5.9053783763725205 },
          { "x": "31", "y": 6.432929112161061 },
          { "x": "32", "y": 7.019479593278558 },
          { "x": "33", "y": 7.669507420223615 },
          { "x": "34", "y": 8.38813263272482 }
        ]
      },
      "longbow-point": -1,
      "stored-energy": {
        "28": 130.2657709879645,
        "34": 210.9791200243716,
        "31.0": 167.079671730019
      }
    },
    {
      "bow-title": "MR Tiron 60\" - 96#@28\"",
      "unstrung-length": "Not Measured",
      "contributed-by": { "facebook": "R Sauqi" },
      "strung-length": "Not Measured",
      "min-box-dim": {
        "length": "Not Measured",
        "width": "Not Measured",
        "depth": "Not Measured"
      },
      "siyahs": {
        "effective-top-length": "Not Measured",
        "effective-bottom-length": "Not Measured",
        "effective-top-angle": "Not Measured",
        "effective-bottom-angle": "Not Measured"
      },
      "bow-mass": "Not Measured",
      "grip-dim": {
        "length": "Not Measured",
        "width": "Not Measured",
        "thickness": "Not Measured"
      },
      "max-limb-thickness": "Not Measured",
      "min-limb-thickness": "Not Measured",
      "max-limb-width": "Not Measured",
      "min-limb-width": "Not Measured",
      "arrow-pass-width": "Not Measured",
      "max-draw": 34,
      "stock-string-length": { "max": "Not Measured", "min": "Not Measured" },
      "brace-height": 20,
      "manufacture-date": "",
      "measurement-date": "",
      "comments": "Measured by R Sauqi",
      "asym": false,
      "asym-length": { "top": "Not Measured", "bottom": "Not Measured" },
      "df-data": [
        { "x": 9, "y": 12.6 },
        { "x": 10, "y": 20.8 },
        { "x": 11, "y": 27.8 },
        { "x": 12, "y": 34 },
        { "x": 13, "y": 38.9 },
        { "x": 14, "y": 44.4 },
        { "x": 15, "y": 49.2 },
        { "x": 16, "y": 53.4 },
        { "x": 17, "y": 57.1 },
        { "x": 18, "y": 61.4 },
        { "x": 19, "y": 64.5 },
        { "x": 20, "y": 68.2 },
        { "x": 21, "y": 71.8 },
        { "x": 22, "y": 75.1 },
        { "x": 23, "y": 79.6 },
        { "x": 24, "y": 83.1 },
        { "x": 25, "y": 87.4 },
        { "x": 26, "y": 92 },
        { "x": 27, "y": 95.7 },
        { "x": 28, "y": 101.3 },
        { "x": 29, "y": 107 },
        { "x": 30, "y": 112.7 },
        { "x": 31, "y": 118.9 },
        { "x": 32, "y": 125.3 },
        { "x": 33, "y": 132 },
        { "x": 34, "y": 140 }
      ],
      "central-differences": [
        { "x": 9.0, "y": 9.158333333333339 },
        { "x": 10.0, "y": 6.633333333333333 },
        { "x": 11.0, "y": 6.608333333333332 },
        { "x": 12.0, "y": 5.433333333333334 },
        { "x": 13.0, "y": 5.15 },
        { "x": 14.0, "y": 5.25 },
        { "x": 15.0, "y": 4.483333333333331 },
        { "x": 16.0, "y": 3.8499999999999988 },
        { "x": 17.0, "y": 4.058333333333337 },
        { "x": 18.0, "y": 3.7000000000000064 },
        { "x": 19.0, "y": 3.308333333333339 },
        { "x": 20.0, "y": 3.7249999999999943 },
        { "x": 21.0, "y": 3.3416666666666615 },
        { "x": 22.0, "y": 3.958333333333341 },
        { "x": 23.0, "y": 4.03333333333333 },
        { "x": 24.0, "y": 3.7916666666666696 },
        { "x": 25.0, "y": 4.59166666666667 },
        { "x": 26.0, "y": 4.016666666666662 },
        { "x": 27.0, "y": 4.566666666666668 },
        { "x": 28.0, "y": 5.80833333333333 },
        { "x": 29.0, "y": 5.6666666666666625 },
        { "x": 30.0, "y": 5.933333333333334 },
        { "x": 31.0, "y": 6.316666666666677 },
        { "x": 32.0, "y": 6.458333333333334 },
        { "x": 33.0, "y": 6.983333333333292 },
        { "x": 34.0, "y": 9.208333333333314 }
      ],
      "regression-estimation": {
        "df-curve": [
          { "x": "9", "y": 12.941359780247417 },
          { "x": "10", "y": 20.891789233632238 },
          { "x": "11", "y": 27.861453085546923 },
          { "x": "12", "y": 34.020597909723335 },
          { "x": "13", "y": 39.51554505965984 },
          { "x": "14", "y": 44.472509762934465 },
          { "x": "15", "y": 49.000856395078436 },
          { "x": "16", "y": 53.195877214857866 },
          { "x": "17", "y": 57.14116871720889 },
          { "x": "18", "y": 60.91066864345903 },
          { "x": "19", "y": 64.57040727664429 },
          { "x": "20", "y": 68.1800186848616 },
          { "x": "21", "y": 71.79405083917081 },
          { "x": "22", "y": 75.46310783942862 },
          { "x": "23", "y": 79.23485267474959 },
          { "x": "24", "y": 83.15489489220711 },
          { "x": "25", "y": 87.2675841354478 },
          { "x": "26", "y": 91.616727648927 },
          { "x": "27", "y": 96.24624744299662 },
          { "x": "28", "y": 101.20079081207487 },
          { "x": "29", "y": 106.52630623518257 },
          { "x": "30", "y": 112.2705953168329 },
          { "x": "31", "y": 118.48385030586971 },
          { "x": "32", "y": 125.21918582614296 },
          { "x": "33", "y": 132.53317273724628 },
          { "x": "34", "y": 140.48638149201864 }
        ],
        "coeffs": [
          -0.16491954526959557, 0.08863980204767231, 33.58869369212589,
          0.40124431143736217, 49.05410132574678
        ],
        "regression-eqn": "-203.6671495620372e^-0.16491954526959557x + -2.4329700326389103e^0.08863980204767231x49.05410132574678",
        "regression-derivative": "33.58869369212589e^-0.16491954526959557x + 0.40124431143736217e^0.08863980204767231x",
        "regression-derivative-values": [
          { "x": "9", "y": 8.504414574099451 },
          { "x": "10", "y": 7.429466362320934 },
          { "x": "11", "y": 6.5381612959013555 },
          { "x": "12", "y": 5.80445183673028 },
          { "x": "13", "y": 5.206424286720094 },
          { "x": "14", "y": 4.725686379265525 },
          { "x": "15", "y": 4.346849471689041 },
          { "x": "16", "y": 4.057091093969377 },
          { "x": "17", "y": 3.845785787601508 },
          { "x": "18", "y": 3.704194016952445 },
          { "x": "19", "y": 3.625200504246256 },
          { "x": "20", "y": 3.6030946709861222 },
          { "x": "21", "y": 3.633386999379961 },
          { "x": "22", "y": 3.7126560878695503 },
          { "x": "23", "y": 3.838421991208901 },
          { "x": "24", "y": 4.009042129789277 },
          { "x": "25", "y": 4.223626643816123 },
          { "x": "26", "y": 4.4819705714240765 },
          { "x": "27", "y": 4.784500659386317 },
          { "x": "28", "y": 5.132234982215141 },
          { "x": "29", "y": 5.526753859921061 },
          { "x": "30", "y": 5.970180834797078 },
          { "x": "31", "y": 6.465172700388647 },
          { "x": "32", "y": 7.014917777318079 },
          { "x": "33", "y": 7.623141805992441 },
          { "x": "34", "y": 8.294120979827746 }
        ]
      },
      "longbow-point": -1,
      "stored-energy": {
        "28": 135.8267756774735,
        "34": 219.70067408474742,
        "31.0": 174.22154578185484
      }
    },
    {
      "bow-title": "MR Tiron 60\" - 88#@28\"",
      "unstrung-length": "Not Measured",
      "contributed-by": { "facebook": "R Sauqi" },
      "strung-length": "Not Measured",
      "min-box-dim": {
        "length": "Not Measured",
        "width": "Not Measured",
        "depth": "Not Measured"
      },
      "siyahs": {
        "effective-top-length": "Not Measured",
        "effective-bottom-length": "Not Measured",
        "effective-top-angle": "Not Measured",
        "effective-bottom-angle": "Not Measured"
      },
      "bow-mass": "Not Measured",
      "grip-dim": {
        "length": "Not Measured",
        "width": "Not Measured",
        "thickness": "Not Measured"
      },
      "max-limb-thickness": "Not Measured",
      "min-limb-thickness": "Not Measured",
      "max-limb-width": "Not Measured",
      "min-limb-width": "Not Measured",
      "arrow-pass-width": "Not Measured",
      "max-draw": 34,
      "stock-string-length": { "max": "Not Measured", "min": "Not Measured" },
      "brace-height": 20,
      "manufacture-date": "",
      "measurement-date": "",
      "comments": "Measured by R Sauqi",
      "asym": false,
      "asym-length": { "top": "Not Measured", "bottom": "Not Measured" },
      "df-data": [
        { "x": 9, "y": 6.2 },
        { "x": 10, "y": 14.8 },
        { "x": 11, "y": 21.5 },
        { "x": 12, "y": 27.9 },
        { "x": 13, "y": 32.6 },
        { "x": 14, "y": 38 },
        { "x": 15, "y": 42.7 },
        { "x": 16, "y": 46.2 },
        { "x": 17, "y": 49.9 },
        { "x": 18, "y": 53.8 },
        { "x": 19, "y": 57.3 },
        { "x": 20, "y": 60.4 },
        { "x": 21, "y": 63.9 },
        { "x": 22, "y": 67.7 },
        { "x": 23, "y": 71.2 },
        { "x": 24, "y": 75.2 },
        { "x": 25, "y": 78.6 },
        { "x": 26, "y": 83 },
        { "x": 27, "y": 87.5 },
        { "x": 28, "y": 91.5 },
        { "x": 29, "y": 96.5 },
        { "x": 30, "y": 102.5 },
        { "x": 31, "y": 108 },
        { "x": 32, "y": 114.3 },
        { "x": 33, "y": 120.5 },
        { "x": 34, "y": 127.9 }
      ],
      "central-differences": [
        { "x": 9.0, "y": 10.83333333333333 },
        { "x": 10.0, "y": 5.433333333333334 },
        { "x": 11.0, "y": 6.53333333333333 },
        { "x": 12.0, "y": 5.46666666666667 },
        { "x": 13.0, "y": 4.966666666666669 },
        { "x": 14.0, "y": 5.208333333333334 },
        { "x": 15.0, "y": 4.025 },
        { "x": 16.0, "y": 3.4833333333333325 },
        { "x": 17.0, "y": 3.8499999999999934 },
        { "x": 18.0, "y": 3.7499999999999982 },
        { "x": 19.0, "y": 3.233333333333338 },
        { "x": 20.0, "y": 3.2416666666666663 },
        { "x": 21.0, "y": 3.708333333333332 },
        { "x": 22.0, "y": 3.633333333333339 },
        { "x": 23.0, "y": 3.774999999999997 },
        { "x": 24.0, "y": 3.6583333333333226 },
        { "x": 25.0, "y": 3.8416666666666597 },
        { "x": 26.0, "y": 4.575000000000003 },
        { "x": 27.0, "y": 4.1750000000000025 },
        { "x": 28.0, "y": 4.374999999999998 },
        { "x": 29.0, "y": 5.624999999999993 },
        { "x": 30.0, "y": 5.766666666666673 },
        { "x": 31.0, "y": 5.866666666666658 },
        { "x": 32.0, "y": 6.21666666666666 },
        { "x": 33.0, "y": 5.2999999999999545 },
        { "x": 34.0, "y": 8.983333333333235 }
      ],
      "regression-estimation": {
        "df-curve": [
          { "x": "9", "y": 6.608016695816804 },
          { "x": "10", "y": 14.99870661269835 },
          { "x": "11", "y": 22.109740760772063 },
          { "x": "12", "y": 28.210517976491648 },
          { "x": "13", "y": 33.520807491508705 },
          { "x": "14", "y": 38.220381753596776 },
          { "x": "15", "y": 42.456818277677165 },
          { "x": "16", "y": 46.35182145329861 },
          { "x": "17", "y": 50.006348198137225 },
          { "x": "18", "y": 53.504767133086794 },
          { "x": "19", "y": 56.91823711184479 },
          { "x": "20", "y": 60.307455483878954 },
          { "x": "21", "y": 63.72489780072936 },
          { "x": "22", "y": 67.21664749485414 },
          { "x": "23", "y": 70.82389531876764 },
          { "x": "24", "y": 74.58417318175066 },
          { "x": "25", "y": 78.53237477587373 },
          { "x": "26", "y": 82.70160548763253 },
          { "x": "27", "y": 87.12389609745064 },
          { "x": "28", "y": 91.83080831380377 },
          { "x": "29", "y": 96.85395497834381 },
          { "x": "30", "y": 102.22545357589068 },
          { "x": "31", "y": 107.97832829668859 },
          { "x": "32", "y": 114.14687317280507 },
          { "x": "33", "y": 120.7669866206334 },
          { "x": "34", "y": 127.87648596582449 }
        ],
        "coeffs": [
          -0.21221365699483544, 0.07336528436966361, 53.780061202534064,
          0.6048680235551602, 28.181860273722137
        ],
        "regression-eqn": "-253.42412907875618e^-0.21221365699483544x + -2.850278498192417e^0.07336528436966361x28.181860273722137",
        "regression-derivative": "53.780061202534064e^-0.21221365699483544x + 0.6048680235551602e^0.07336528436966361x",
        "regression-derivative-values": [
          { "x": "9", "y": 9.135016773992891 },
          { "x": "10", "y": 7.701273989746316 },
          { "x": "11", "y": 6.565497086401183 },
          { "x": "12", "y": 5.672526028480395 },
          { "x": "13", "y": 4.977885874631212 },
          { "x": "14", "y": 4.445754209454405 },
          { "x": "15", "y": 4.047318018837354 },
          { "x": "16", "y": 3.7594456049242995 },
          { "x": "17", "y": 3.563613368116517 },
          { "x": "18", "y": 3.445038793974928 },
          { "x": "19", "y": 3.391980292860077 },
          { "x": "20", "y": 3.3951720703749193 },
          { "x": "21", "y": 3.447368297504866 },
          { "x": "22", "y": 3.5429757760358473 },
          { "x": "23", "y": 3.6777582800041815 },
          { "x": "24", "y": 3.848598977655676 },
          { "x": "25", "y": 4.0533099463025986 },
          { "x": "26", "y": 4.290479902359176 },
          { "x": "27", "y": 4.559352975982745 },
          { "x": "28", "y": 4.859732741208789 },
          { "x": "29", "y": 5.191906830573519 },
          { "x": "30", "y": 5.55658836838327 },
          { "x": "31", "y": 5.95487118979649 },
          { "x": "32", "y": 6.38819640671932 },
          { "x": "33", "y": 6.858328362865576 },
          { "x": "34", "y": 7.367338410784987 }
        ]
      },
      "longbow-point": -1,
      "stored-energy": {
        "28": 119.66138942741003,
        "34": 195.98924361793516,
        "31.0": 154.6031621483135
      }
    }
  ]
}
